cli.py
cluster_affinity/__init__.py
cluster_affinity/cli.py
cluster_affinity/config.py
cluster_affinity/matrix.py
cluster_affinity/reader.py
cluster_affinity/utils.py
cluster_affinity/visualization.py
cluster_affinity/cluster_computation/__init__.py
cluster_affinity/cluster_computation/cluster_affinity.py
cluster_affinity/cluster_computation/heavy_path_decompositions.py
cluster_affinity/cluster_computation/heavy_trees.py
cluster_affinity/cluster_computation/transfer_index.py
cluster_affinity/test/__init__.py
cluster_affinity/test/test_cli.py
cluster_affinity/test/test_clustertree.py
cluster_affinity/test/test_heavy_trees.py
cluster_affinity/test/test_reader.py
cluster_affinity-0.7.3.dist-info/licenses/LICENSE
cluster_affinity-0.7.3.dist-info/METADATA
cluster_affinity-0.7.3.dist-info/WHEEL
cluster_affinity-0.7.3.dist-info/entry_points.txt
cluster_affinity-0.7.3.dist-info/top_level.txt
cluster_affinity-0.7.3.dist-info/RECORD
