Metadata-Version: 2.4
Name: cluster_affinity
Version: 0.7.3
Summary: A tool to calculate the cluster affinity distance between two trees
Author-email: Sanket Wagle <swagle@iastate.edu>
Project-URL: Homepage, https://github.com/swagle8987/cluster_affinity
Project-URL: Issues, https://github.com/swagle8987/cluster_affinity/issues
License-File: LICENSE
Requires-Dist: ete4
Requires-Dist: matplotlib
Requires-Dist: alive-progress
Dynamic: license-file
